{
    "key": "group_592293ef20b47",
    "title": "Colophon",
    "fields": [
        {
            "key": "field_592293fa1add8",
            "label": "Authors",
            "name": "authors",
            "type": "wysiwyg",
            "instructions": "",
            "required": 0,
            "conditional_logic": 0,
            "wrapper": {
                "width": "",
                "class": "",
                "id": ""
            },
            "default_value": "",
            "tabs": "all",
            "toolbar": "full",
            "media_upload": 1
        },
        {
            "key": "field_592294151add9",
            "label": "Colophon Column 1",
            "name": "colophon_col_1",
            "type": "wysiwyg",
            "instructions": "",
            "required": 0,
            "conditional_logic": 0,
            "wrapper": {
                "width": "",
                "class": "",
                "id": ""
            },
            "default_value": "",
            "tabs": "all",
            "toolbar": "full",
            "media_upload": 1
        },
        {
            "key": "field_59229ad7a66a6",
            "label": "Colophon Column 2",
            "name": "colophon_col_2",
            "type": "wysiwyg",
            "instructions": "",
            "required": 0,
            "conditional_logic": 0,
            "wrapper": {
                "width": "",
                "class": "",
                "id": ""
            },
            "default_value": "",
            "tabs": "all",
            "toolbar": "full",
            "media_upload": 1
        }
    ],
    "location": [
        [
            {
                "param": "post",
                "operator": "==",
                "value": "27"
            }
        ]
    ],
    "menu_order": 0,
    "position": "normal",
    "style": "default",
    "label_placement": "top",
    "instruction_placement": "label",
    "hide_on_screen": [
        "permalink",
        "the_content",
        "excerpt",
        "custom_fields",
        "discussion",
        "comments",
        "revisions",
        "slug",
        "author",
        "format",
        "page_attributes",
        "featured_image",
        "categories",
        "tags",
        "send-trackbacks"
    ],
    "active": 1,
    "description": "",
    "modified": 1495440117
}